{
    "AAC": "2024-03-13",
    "ACC": "2024-03-12",
    "AEC": "2024-03-09",
    "A-Sun": "2024-03-04",
    "A-10": "2024-03-12",
    "Big 12": "2024-03-12",
    "Big East": "2024-03-13",
    "Big Sky": "2024-03-09",
    "Big South": "2024-03-06",
    "Big Ten": "2024-03-13",
    "Big West": "2024-03-13",
    "CUSA": "2024-03-12",
    "CAA": "2024-03-08",
    "Horizon": "2024-03-05",
    "Ivy": "2024-03-16",
    "MAAC": "2024-03-12",
    "MAC": "2024-03-14",
    "MEAC": "2024-03-13",
    "MVC": "2024-03-07",
    "MWC": "2024-03-13",
    "NEC": "2024-03-06",
    "OVC": "2024-03-06",
    "Pac-12": "2024-03-13",
    "Patriot": "2024-03-05",
    "SEC": "2024-03-13",
    "Southern": "2024-03-08",
    "Southland": "2024-03-10",
    "Summit": "2024-03-08",
    "Sun Belt": "2024-03-05",
    "SWAC": "2024-03-13",
    "WAC": "2024-03-13",
    "WCC": "2024-03-07"
}
